adb_android/__init__.py
adb_android/adb_android.py
adb_android/var.py
adb_android-1.4.0.dist-info/METADATA
adb_android-1.4.0.dist-info/RECORD
adb_android-1.4.0.dist-info/WHEEL
adb_android-1.4.0.dist-info/top_level.txt
